jsonschemaplus/__init__.py
jsonschemaplus/errors.py
jsonschemaplus/validators.py
jsonschemaplus-0.0.1.dev1.dist-info/DESCRIPTION.rst
jsonschemaplus-0.0.1.dev1.dist-info/LICENSE.txt
jsonschemaplus-0.0.1.dev1.dist-info/METADATA
jsonschemaplus-0.0.1.dev1.dist-info/RECORD
jsonschemaplus-0.0.1.dev1.dist-info/WHEEL
jsonschemaplus-0.0.1.dev1.dist-info/metadata.json
jsonschemaplus-0.0.1.dev1.dist-info/top_level.txt
